zpl2.py
zpl2-1.2.1.dist-info/LICENSE.txt
zpl2-1.2.1.dist-info/METADATA
zpl2-1.2.1.dist-info/WHEEL
zpl2-1.2.1.dist-info/top_level.txt
zpl2-1.2.1.dist-info/RECORD
