Metadata-Version: 2.1
Name: zpl2
Version: 1.2.1
Summary: Python library that generates ZPL II labels
Author: Sylvain Garancher
Author-email: sylvain.garancher@syleam.fr
License: LICENSE.txt
License-File: LICENSE.txt
Provides-Extra: graphics
Requires-Dist: pillow ; extra == 'graphics'
